LICENSE.txt
MANIFEST.in
NEWS.rst
README.rst
setup.py
setup_helpers.py
flufl.flake8.egg-info/PKG-INFO
flufl.flake8.egg-info/SOURCES.txt
flufl.flake8.egg-info/dependency_links.txt
flufl.flake8.egg-info/entry_points.txt
flufl.flake8.egg-info/namespace_packages.txt
flufl.flake8.egg-info/top_level.txt
flufl/flake8/__init__.py
flufl/flake8/imports.py