Metadata-Version: 1.2
Name: flufl.flake8
Version: 0.10
Summary: A flake8 plugin for GNU Mailman import order
Home-page: https://gitlab.com/warsaw/flufl.flake8
Maintainer: Barry Warsaw
Maintainer-email: barry@python.org
License: ASLv2
Download-URL: https://pypi.python.org/pypi/flufl.flake8
Platform: UNKNOWN
Classifier: Development Status :: 4 - Beta
Classifier: Environment :: Plugins
Classifier: Intended Audience :: Developers
Classifier: License :: OSI Approved :: Apache Software License
Classifier: Programming Language :: Python :: 3
